<?xml version="1.0"?>
<document><category nombre="3" img="Girls_balk_3.jpg"><description></description><name>Tanks</name><product id="212" quantity="0" reduction="0" price="&lt;span class=&quot;price&quot;&gt;&#x20AC;&#xA0;34,95&lt;/span&gt;"><title>Funny Fleur - SimplyGreen</title><description>Hemdje</description><cover>http://webstore.no-tomatoes.com/media/catalog/product/2/9/298-funnyfleur-green.jpg</cover></product><product id="216" quantity="0" reduction="0" price="&lt;span class=&quot;price&quot;&gt;&#x20AC;&#xA0;34,95&lt;/span&gt;"><title>Funny Fleur - Smoke</title><description>Hemdje</description><cover>http://webstore.no-tomatoes.com/media/catalog/product/2/9/298-funnyfleur-smoke.jpg</cover></product><product id="219" quantity="0" reduction="0" price="&lt;span class=&quot;price&quot;&gt;&#x20AC;&#xA0;34,95&lt;/span&gt;"><title>Funny Fleur - VeryBerry</title><description>Hemdje</description><cover>http://webstore.no-tomatoes.com/media/catalog/product/2/9/298-funnyfleur-veryberry.jpg</cover></product></category></document>
