<?xml version="1.0"?>
<document><category nombre="9" img="Boys_balk_1.jpg"><description>Tee's</description><name>Tee's</name><product id="133" quantity="0" reduction="0" price="&lt;span class=&quot;price&quot;&gt;&#x20AC;&#xA0;34,95&lt;/span&gt;"><title>Cheesy Elliot Muscle</title><description>Topshirt met handtekeningen van bekende Amerikaanse honkbalspelers</description><cover>http://webstore.no-tomatoes.com/media/catalog/product/2/6/269-cheesyelliot-muscle_smoke.jpg</cover></product><product id="140" quantity="0" reduction="0" price="&lt;span class=&quot;price&quot;&gt;&#x20AC;&#xA0;34,95&lt;/span&gt;"><title>Cheesy Elliot Roppongi</title><description>Leuk shirt geinspireerd op het uitgaansgebied in Tokyo, Roppongi</description><cover>http://webstore.no-tomatoes.com/media/catalog/product/2/7/271-cheesyelliot-roppongi-stonewash.jpg</cover></product><product id="149" quantity="0" reduction="0" price="&lt;span class=&quot;price&quot;&gt;&#x20AC;&#xA0;34,95&lt;/span&gt;"><title>Lunatic Kane Smoke/Cloud</title><description>Shortsleeve T in katoen/elastan met grote N op de voorkant.&#xD;
Ook na het wassen blijft dit T-shirt perfect in model en geen zorgen; strijken hoeft niet! </description><cover>http://webstore.no-tomatoes.com/media/catalog/product/2/7/273-lunatic-smoke.jpg</cover></product><product id="155" quantity="0" reduction="0" price="&lt;span class=&quot;price&quot;&gt;&#x20AC;&#xA0;34,95&lt;/span&gt;"><title>Lunatic Kane StoneWash/Cloud</title><description>Shortsleeve T in katoen/elastan met stoere vintage print op de voorkant.&#xD;
Ook na het wassen blijft dit T-shirt perfect in model en geen zorgen; strijken hoeft niet! </description><cover>http://webstore.no-tomatoes.com/media/catalog/product/2/7/273-lunatic-stonewash.jpg</cover></product><product id="262" quantity="0" reduction="0" price="&lt;span class=&quot;price&quot;&gt;&#x20AC;&#xA0;34,95&lt;/span&gt;"><title>Cheesy Elliot That Fresh</title><description>Shortsleeve T in katoen/elastan met stoer artwork.  &#xD;
Ook na het wassen blijft dit T-shirt perfect in model en geen zorgen; strijken hoeft niet!</description><cover>http://webstore.no-tomatoes.com/media/catalog/product/3/0/307-cheesyelliot-thatfresh-azure_2.jpg</cover></product><product id="279" quantity="0" reduction="0" price="&lt;span class=&quot;price&quot;&gt;&#x20AC;&#xA0;34,95&lt;/span&gt;"><title>Cheesy Elliot Honolulu</title><description>Shortsleeve T in katoen/elastan met stoer surf-artwork.  &#xD;
Ook na het wassen blijft dit T-shirt perfect in model en geen zorgen; strijken hoeft niet!</description><cover>http://webstore.no-tomatoes.com/media/catalog/product/3/0/306-cheesyelliot-honolulu-green_1.jpg</cover></product><product id="285" quantity="0" reduction="0" price="&lt;span class=&quot;price&quot;&gt;&#x20AC;&#xA0;34,95&lt;/span&gt;"><title>Cheesy Elliot Bandage</title><description>Shortsleeve T in katoen/elastan met stoer artwork.&#xD;
Ook na het wassen blijft dit T-shirt perfect in model en geen zorgen; strijken hoeft niet! </description><cover>http://webstore.no-tomatoes.com/media/catalog/product/3/0/305-cheesyelliot-bandage-stonewash_1.jpg</cover></product><product id="289" quantity="0" reduction="0" price="&lt;span class=&quot;price&quot;&gt;&#x20AC;&#xA0;34,95&lt;/span&gt;"><title>Cheesy Elliot 23 White</title><description>Shortsleeve T in katoen/elastan met stoer artwork.&#xD;
Ook na het wassen blijft dit T-shirt perfect in model en geen zorgen; strijken hoeft niet! </description><cover>http://webstore.no-tomatoes.com/media/catalog/product/3/0/303-cheesyelliot-23-white_1.jpg</cover></product><product id="294" quantity="0" reduction="0" price="&lt;span class=&quot;price&quot;&gt;&#x20AC;&#xA0;34,95&lt;/span&gt;"><title>Cheesy Elliot 23 Red</title><description>Coole T in katoen/elastan met stoer artwork.&#xD;
Ook na het wassen blijft dit T-shirt perfect in model en geen zorgen; strijken hoeft niet! </description><cover>http://webstore.no-tomatoes.com/media/catalog/product/3/0/303-cheesyelliot-23-tomato_1.jpg</cover></product></category></document>
